{
  "metadata": {
    "version": "1.0",
    "createdAt": "2025-04-15T13:39:14.618118",
    "editor": "FSM Visualizer"
  },
  "layout": {
    "mainCanvas": {
      "width": 400,
      "height": 500
    },
    "panelCanvas": {
      "x": 400,
      "width": 200,
      "height": 500
    }
  },
  "states": [
    {
      "id": "s_0f8165",
      "type": "state",
      "label": "INI",
      "x": 57.5,
      "y": 42.5,
      "width": 45,
      "height": 35,
      "style": {
        "fillColor": "#a7d7a7",
        "borderColor": "#3a7ca5",
        "textColor": "#2f2f2f",
        "fontSize": 8,
        "shape": "circle"
      },
      "properties": {
        "fullName": "INIT",
        "description": "INIT state"
      }
    },
    {
      "id": "s_9807e2",
      "type": "state",
      "label": "CON",
      "x": 137.5,
      "y": 42.5,
      "width": 45,
      "height": 35,
      "style": {
        "fillColor": "#d4e6f1",
        "borderColor": "#3a7ca5",
        "textColor": "#2f2f2f",
        "fontSize": 8,
        "shape": "roundrect"
      },
      "properties": {
        "fullName": "CONNECT",
        "description": "CONNECT state"
      }
    },
    {
      "id": "s_872a87",
      "type": "state",
      "label": "CON",
      "x": 217.5,
      "y": 42.5,
      "width": 45,
      "height": 35,
      "style": {
        "fillColor": "#d4e6f1",
        "borderColor": "#3a7ca5",
        "textColor": "#2f2f2f",
        "fontSize": 8,
        "shape": "roundrect"
      },
      "properties": {
        "fullName": "CONNACK",
        "description": "CONNACK state"
      }
    },
    {
      "id": "s_2eb201",
      "type": "state",
      "label": "PUB",
      "x": 297.5,
      "y": 42.5,
      "width": 45,
      "height": 35,
      "style": {
        "fillColor": "#d4e6f1",
        "borderColor": "#3a7ca5",
        "textColor": "#2f2f2f",
        "fontSize": 8,
        "shape": "roundrect"
      },
      "properties": {
        "fullName": "PUBLISH",
        "description": "PUBLISH state"
      }
    },
    {
      "id": "s_e5c098",
      "type": "state",
      "label": "PUB",
      "x": 57.5,
      "y": 142.5,
      "width": 45,
      "height": 35,
      "style": {
        "fillColor": "#d4e6f1",
        "borderColor": "#3a7ca5",
        "textColor": "#2f2f2f",
        "fontSize": 8,
        "shape": "roundrect"
      },
      "properties": {
        "fullName": "PUBACK",
        "description": "PUBACK state"
      }
    },
    {
      "id": "s_aad800",
      "type": "state",
      "label": "PUB",
      "x": 137.5,
      "y": 142.5,
      "width": 45,
      "height": 35,
      "style": {
        "fillColor": "#d4e6f1",
        "borderColor": "#3a7ca5",
        "textColor": "#2f2f2f",
        "fontSize": 8,
        "shape": "roundrect"
      },
      "properties": {
        "fullName": "PUBREC",
        "description": "PUBREC state"
      }
    },
    {
      "id": "s_622914",
      "type": "state",
      "label": "PUB",
      "x": 217.5,
      "y": 142.5,
      "width": 45,
      "height": 35,
      "style": {
        "fillColor": "#d4e6f1",
        "borderColor": "#3a7ca5",
        "textColor": "#2f2f2f",
        "fontSize": 8,
        "shape": "roundrect"
      },
      "properties": {
        "fullName": "PUBREL",
        "description": "PUBREL state"
      }
    },
    {
      "id": "s_ef96b6",
      "type": "state",
      "label": "PUB",
      "x": 297.5,
      "y": 142.5,
      "width": 45,
      "height": 35,
      "style": {
        "fillColor": "#d4e6f1",
        "borderColor": "#3a7ca5",
        "textColor": "#2f2f2f",
        "fontSize": 8,
        "shape": "roundrect"
      },
      "properties": {
        "fullName": "PUBCOMP",
        "description": "PUBCOMP state"
      }
    },
    {
      "id": "s_03ff0d",
      "type": "state",
      "label": "SUB",
      "x": 57.5,
      "y": 242.5,
      "width": 45,
      "height": 35,
      "style": {
        "fillColor": "#d4e6f1",
        "borderColor": "#3a7ca5",
        "textColor": "#2f2f2f",
        "fontSize": 8,
        "shape": "roundrect"
      },
      "properties": {
        "fullName": "SUBSCRIBE",
        "description": "SUBSCRIBE state"
      }
    },
    {
      "id": "s_500381",
      "type": "state",
      "label": "SUB",
      "x": 137.5,
      "y": 242.5,
      "width": 45,
      "height": 35,
      "style": {
        "fillColor": "#d4e6f1",
        "borderColor": "#3a7ca5",
        "textColor": "#2f2f2f",
        "fontSize": 8,
        "shape": "roundrect"
      },
      "properties": {
        "fullName": "SUBACK",
        "description": "SUBACK state"
      }
    },
    {
      "id": "s_e5b78f",
      "type": "state",
      "label": "UNS",
      "x": 217.5,
      "y": 242.5,
      "width": 45,
      "height": 35,
      "style": {
        "fillColor": "#d4e6f1",
        "borderColor": "#3a7ca5",
        "textColor": "#2f2f2f",
        "fontSize": 8,
        "shape": "roundrect"
      },
      "properties": {
        "fullName": "UNSUBSCRIBE",
        "description": "UNSUBSCRIBE state"
      }
    },
    {
      "id": "s_c01667",
      "type": "state",
      "label": "UNS",
      "x": 297.5,
      "y": 242.5,
      "width": 45,
      "height": 35,
      "style": {
        "fillColor": "#d4e6f1",
        "borderColor": "#3a7ca5",
        "textColor": "#2f2f2f",
        "fontSize": 8,
        "shape": "roundrect"
      },
      "properties": {
        "fullName": "UNSUBACK",
        "description": "UNSUBACK state"
      }
    },
    {
      "id": "s_2edf68",
      "type": "state",
      "label": "PIN",
      "x": 57.5,
      "y": 342.5,
      "width": 45,
      "height": 35,
      "style": {
        "fillColor": "#d4e6f1",
        "borderColor": "#3a7ca5",
        "textColor": "#2f2f2f",
        "fontSize": 8,
        "shape": "roundrect"
      },
      "properties": {
        "fullName": "PINGREQ",
        "description": "PINGREQ state"
      }
    },
    {
      "id": "s_6898c3",
      "type": "state",
      "label": "PIN",
      "x": 137.5,
      "y": 342.5,
      "width": 45,
      "height": 35,
      "style": {
        "fillColor": "#d4e6f1",
        "borderColor": "#3a7ca5",
        "textColor": "#2f2f2f",
        "fontSize": 8,
        "shape": "roundrect"
      },
      "properties": {
        "fullName": "PINGRESP",
        "description": "PINGRESP state"
      }
    },
    {
      "id": "s_71b485",
      "type": "state",
      "label": "DIS",
      "x": 217.5,
      "y": 342.5,
      "width": 45,
      "height": 35,
      "style": {
        "fillColor": "#d4e6f1",
        "borderColor": "#3a7ca5",
        "textColor": "#2f2f2f",
        "fontSize": 8,
        "shape": "roundrect"
      },
      "properties": {
        "fullName": "DISCONNECT",
        "description": "DISCONNECT state"
      }
    }
  ],
  "transitions": [
    {
      "id": "t_3b215f",
      "type": "transition",
      "from": "s_0f8165",
      "to": "s_9807e2",
      "label": "→",
      "style": {
        "lineColor": "#5d5d5d",
        "lineWidth": 1.2,
        "fontSize": 7,
        "textColor": "#333333"
      },
      "properties": {
        "fullAction": "Transition",
        "condition": "init to connect"
      }
    },
    {
      "id": "t_81d779",
      "type": "transition",
      "from": "s_9807e2",
      "to": "s_872a87",
      "label": "Wt",
      "style": {
        "lineColor": "#5d5d5d",
        "lineWidth": 1.2,
        "fontSize": 7,
        "textColor": "#333333"
      },
      "properties": {
        "fullAction": "Wait",
        "condition": "connect sent, waiting for connack"
      }
    },
    {
      "id": "t_1df57d",
      "type": "transition",
      "from": "s_872a87",
      "to": "s_2eb201",
      "label": "→",
      "style": {
        "lineColor": "#5d5d5d",
        "lineWidth": 1.2,
        "fontSize": 7,
        "textColor": "#333333"
      },
      "properties": {
        "fullAction": "Transition",
        "condition": "connected, can publish"
      }
    },
    {
      "id": "t_969e24",
      "type": "transition",
      "from": "s_872a87",
      "to": "s_03ff0d",
      "label": "→",
      "style": {
        "lineColor": "#5d5d5d",
        "lineWidth": 1.2,
        "fontSize": 7,
        "textColor": "#333333"
      },
      "properties": {
        "fullAction": "Transition",
        "condition": "connected, can subscribe"
      }
    },
    {
      "id": "t_4bd2d3",
      "type": "transition",
      "from": "s_872a87",
      "to": "s_e5b78f",
      "label": "→",
      "style": {
        "lineColor": "#5d5d5d",
        "lineWidth": 1.2,
        "fontSize": 7,
        "textColor": "#333333"
      },
      "properties": {
        "fullAction": "Transition",
        "condition": "connected, can unsubscribe"
      }
    },
    {
      "id": "t_1f1e71",
      "type": "transition",
      "from": "s_872a87",
      "to": "s_2edf68",
      "label": "→",
      "style": {
        "lineColor": "#5d5d5d",
        "lineWidth": 1.2,
        "fontSize": 7,
        "textColor": "#333333"
      },
      "properties": {
        "fullAction": "Transition",
        "condition": "keep - alive, send pingreq"
      }
    },
    {
      "id": "t_b76f24",
      "type": "transition",
      "from": "s_872a87",
      "to": "s_71b485",
      "label": "→",
      "style": {
        "lineColor": "#5d5d5d",
        "lineWidth": 1.2,
        "fontSize": 7,
        "textColor": "#333333"
      },
      "properties": {
        "fullAction": "Transition",
        "condition": "disconnect request"
      }
    },
    {
      "id": "t_d7d180",
      "type": "transition",
      "from": "s_2eb201",
      "to": "s_e5c098",
      "label": "Wt",
      "style": {
        "lineColor": "#5d5d5d",
        "lineWidth": 1.2,
        "fontSize": 7,
        "textColor": "#333333"
      },
      "properties": {
        "fullAction": "Wait",
        "condition": "qos 1, wait for puback"
      }
    },
    {
      "id": "t_c7d94c",
      "type": "transition",
      "from": "s_2eb201",
      "to": "s_aad800",
      "label": "Wt",
      "style": {
        "lineColor": "#5d5d5d",
        "lineWidth": 1.2,
        "fontSize": 7,
        "textColor": "#333333"
      },
      "properties": {
        "fullAction": "Wait",
        "condition": "qos 2, wait for pubrec"
      }
    },
    {
      "id": "t_ed6b6b",
      "type": "transition",
      "from": "s_e5c098",
      "to": "s_2eb201",
      "label": "Rcv",
      "style": {
        "lineColor": "#5d5d5d",
        "lineWidth": 1.2,
        "fontSize": 7,
        "textColor": "#333333"
      },
      "properties": {
        "fullAction": "Receive",
        "condition": "puback received, can publish again"
      }
    },
    {
      "id": "t_70db98",
      "type": "transition",
      "from": "s_aad800",
      "to": "s_622914",
      "label": "Rcv",
      "style": {
        "lineColor": "#5d5d5d",
        "lineWidth": 1.2,
        "fontSize": 7,
        "textColor": "#333333"
      },
      "properties": {
        "fullAction": "Receive",
        "condition": "pubrec received, send pubrel"
      }
    },
    {
      "id": "t_1bdadf",
      "type": "transition",
      "from": "s_622914",
      "to": "s_ef96b6",
      "label": "Wt",
      "style": {
        "lineColor": "#5d5d5d",
        "lineWidth": 1.2,
        "fontSize": 7,
        "textColor": "#333333"
      },
      "properties": {
        "fullAction": "Wait",
        "condition": "pubrel sent, wait for pubcomp"
      }
    },
    {
      "id": "t_c269c4",
      "type": "transition",
      "from": "s_ef96b6",
      "to": "s_2eb201",
      "label": "Rcv",
      "style": {
        "lineColor": "#5d5d5d",
        "lineWidth": 1.2,
        "fontSize": 7,
        "textColor": "#333333"
      },
      "properties": {
        "fullAction": "Receive",
        "condition": "pubcomp received, can publish again"
      }
    },
    {
      "id": "t_eb0466",
      "type": "transition",
      "from": "s_03ff0d",
      "to": "s_500381",
      "label": "Wt",
      "style": {
        "lineColor": "#5d5d5d",
        "lineWidth": 1.2,
        "fontSize": 7,
        "textColor": "#333333"
      },
      "properties": {
        "fullAction": "Wait",
        "condition": "subscribe sent, wait for suback"
      }
    },
    {
      "id": "t_795104",
      "type": "transition",
      "from": "s_500381",
      "to": "s_2eb201",
      "label": "Rcv",
      "style": {
        "lineColor": "#5d5d5d",
        "lineWidth": 1.2,
        "fontSize": 7,
        "textColor": "#333333"
      },
      "properties": {
        "fullAction": "Receive",
        "condition": "suback received, can publish"
      }
    },
    {
      "id": "t_15c023",
      "type": "transition",
      "from": "s_e5b78f",
      "to": "s_c01667",
      "label": "Wt",
      "style": {
        "lineColor": "#5d5d5d",
        "lineWidth": 1.2,
        "fontSize": 7,
        "textColor": "#333333"
      },
      "properties": {
        "fullAction": "Wait",
        "condition": "unsubscribe sent, wait for unsuback"
      }
    },
    {
      "id": "t_a55a4d",
      "type": "transition",
      "from": "s_c01667",
      "to": "s_2eb201",
      "label": "Rcv",
      "style": {
        "lineColor": "#5d5d5d",
        "lineWidth": 1.2,
        "fontSize": 7,
        "textColor": "#333333"
      },
      "properties": {
        "fullAction": "Receive",
        "condition": "unsuback received, can publish"
      }
    },
    {
      "id": "t_b2d66c",
      "type": "transition",
      "from": "s_2edf68",
      "to": "s_6898c3",
      "label": "Wt",
      "style": {
        "lineColor": "#5d5d5d",
        "lineWidth": 1.2,
        "fontSize": 7,
        "textColor": "#333333"
      },
      "properties": {
        "fullAction": "Wait",
        "condition": "pingreq sent, wait for pingresp"
      }
    },
    {
      "id": "t_8badfc",
      "type": "transition",
      "from": "s_6898c3",
      "to": "s_2eb201",
      "label": "Rcv",
      "style": {
        "lineColor": "#5d5d5d",
        "lineWidth": 1.2,
        "fontSize": 7,
        "textColor": "#333333"
      },
      "properties": {
        "fullAction": "Receive",
        "condition": "pingresp received, can publish"
      }
    },
    {
      "id": "t_ff35c6",
      "type": "transition",
      "from": "s_71b485",
      "to": "s_0f8165",
      "label": "→",
      "style": {
        "lineColor": "#5d5d5d",
        "lineWidth": 1.2,
        "fontSize": 7,
        "textColor": "#333333"
      },
      "properties": {
        "fullAction": "Transition",
        "condition": "disconnected, back to init"
      }
    }
  ],
  "annotations": [
    {
      "id": "desc_s_0f8165",
      "type": "stateDescription",
      "stateId": "s_0f8165",
      "title": "INIT",
      "content": "INIT state description",
      "position": {
        "row": 0,
        "col": 0
      }
    },
    {
      "id": "desc_s_9807e2",
      "type": "stateDescription",
      "stateId": "s_9807e2",
      "title": "CONNECT",
      "content": "CONNECT state description",
      "position": {
        "row": 1,
        "col": 0
      }
    },
    {
      "id": "desc_s_872a87",
      "type": "stateDescription",
      "stateId": "s_872a87",
      "title": "CONNACK",
      "content": "CONNACK state description",
      "position": {
        "row": 2,
        "col": 0
      }
    },
    {
      "id": "desc_s_2eb201",
      "type": "stateDescription",
      "stateId": "s_2eb201",
      "title": "PUBLISH",
      "content": "PUBLISH state description",
      "position": {
        "row": 3,
        "col": 0
      }
    },
    {
      "id": "desc_s_e5c098",
      "type": "stateDescription",
      "stateId": "s_e5c098",
      "title": "PUBACK",
      "content": "PUBACK state description",
      "position": {
        "row": 4,
        "col": 0
      }
    },
    {
      "id": "desc_s_aad800",
      "type": "stateDescription",
      "stateId": "s_aad800",
      "title": "PUBREC",
      "content": "PUBREC state description",
      "position": {
        "row": 5,
        "col": 0
      }
    },
    {
      "id": "desc_s_622914",
      "type": "stateDescription",
      "stateId": "s_622914",
      "title": "PUBREL",
      "content": "PUBREL state description",
      "position": {
        "row": 6,
        "col": 0
      }
    },
    {
      "id": "desc_s_ef96b6",
      "type": "stateDescription",
      "stateId": "s_ef96b6",
      "title": "PUBCOMP",
      "content": "PUBCOMP state description",
      "position": {
        "row": 7,
        "col": 0
      }
    },
    {
      "id": "desc_s_03ff0d",
      "type": "stateDescription",
      "stateId": "s_03ff0d",
      "title": "SUBSCRIBE",
      "content": "SUBSCRIBE state description",
      "position": {
        "row": 8,
        "col": 0
      }
    },
    {
      "id": "desc_s_500381",
      "type": "stateDescription",
      "stateId": "s_500381",
      "title": "SUBACK",
      "content": "SUBACK state description",
      "position": {
        "row": 9,
        "col": 0
      }
    },
    {
      "id": "desc_s_e5b78f",
      "type": "stateDescription",
      "stateId": "s_e5b78f",
      "title": "UNSUBSCRIBE",
      "content": "UNSUBSCRIBE state description",
      "position": {
        "row": 10,
        "col": 0
      }
    },
    {
      "id": "desc_s_c01667",
      "type": "stateDescription",
      "stateId": "s_c01667",
      "title": "UNSUBACK",
      "content": "UNSUBACK state description",
      "position": {
        "row": 11,
        "col": 0
      }
    },
    {
      "id": "desc_s_2edf68",
      "type": "stateDescription",
      "stateId": "s_2edf68",
      "title": "PINGREQ",
      "content": "PINGREQ state description",
      "position": {
        "row": 12,
        "col": 0
      }
    },
    {
      "id": "desc_s_6898c3",
      "type": "stateDescription",
      "stateId": "s_6898c3",
      "title": "PINGRESP",
      "content": "PINGRESP state description",
      "position": {
        "row": 13,
        "col": 0
      }
    },
    {
      "id": "desc_s_71b485",
      "type": "stateDescription",
      "stateId": "s_71b485",
      "title": "DISCONNECT",
      "content": "DISCONNECT state description",
      "position": {
        "row": 14,
        "col": 0
      }
    },
    {
      "id": "desc_t_3b215f",
      "type": "transitionDescription",
      "transitionId": "t_3b215f",
      "title": "Transition",
      "content": "From: INIT\nTo: CONNECT\nCondition: init to connect",
      "position": {
        "row": 15,
        "col": 0
      }
    },
    {
      "id": "desc_t_81d779",
      "type": "transitionDescription",
      "transitionId": "t_81d779",
      "title": "Wait",
      "content": "From: CONNECT\nTo: CONNACK\nCondition: connect sent, waiting for connack",
      "position": {
        "row": 16,
        "col": 0
      }
    },
    {
      "id": "desc_t_1df57d",
      "type": "transitionDescription",
      "transitionId": "t_1df57d",
      "title": "Transition",
      "content": "From: CONNACK\nTo: PUBLISH\nCondition: connected, can publish",
      "position": {
        "row": 17,
        "col": 0
      }
    },
    {
      "id": "desc_t_969e24",
      "type": "transitionDescription",
      "transitionId": "t_969e24",
      "title": "Transition",
      "content": "From: CONNACK\nTo: SUBSCRIBE\nCondition: connected, can subscribe",
      "position": {
        "row": 18,
        "col": 0
      }
    },
    {
      "id": "desc_t_4bd2d3",
      "type": "transitionDescription",
      "transitionId": "t_4bd2d3",
      "title": "Transition",
      "content": "From: CONNACK\nTo: UNSUBSCRIBE\nCondition: connected, can unsubscribe",
      "position": {
        "row": 19,
        "col": 0
      }
    },
    {
      "id": "desc_t_1f1e71",
      "type": "transitionDescription",
      "transitionId": "t_1f1e71",
      "title": "Transition",
      "content": "From: CONNACK\nTo: PINGREQ\nCondition: keep - alive, send pingreq",
      "position": {
        "row": 20,
        "col": 0
      }
    },
    {
      "id": "desc_t_b76f24",
      "type": "transitionDescription",
      "transitionId": "t_b76f24",
      "title": "Transition",
      "content": "From: CONNACK\nTo: DISCONNECT\nCondition: disconnect request",
      "position": {
        "row": 21,
        "col": 0
      }
    },
    {
      "id": "desc_t_d7d180",
      "type": "transitionDescription",
      "transitionId": "t_d7d180",
      "title": "Wait",
      "content": "From: PUBLISH\nTo: PUBACK\nCondition: qos 1, wait for puback",
      "position": {
        "row": 22,
        "col": 0
      }
    },
    {
      "id": "desc_t_c7d94c",
      "type": "transitionDescription",
      "transitionId": "t_c7d94c",
      "title": "Wait",
      "content": "From: PUBLISH\nTo: PUBREC\nCondition: qos 2, wait for pubrec",
      "position": {
        "row": 23,
        "col": 0
      }
    },
    {
      "id": "desc_t_ed6b6b",
      "type": "transitionDescription",
      "transitionId": "t_ed6b6b",
      "title": "Receive",
      "content": "From: PUBACK\nTo: PUBLISH\nCondition: puback received, can publish again",
      "position": {
        "row": 24,
        "col": 0
      }
    },
    {
      "id": "desc_t_70db98",
      "type": "transitionDescription",
      "transitionId": "t_70db98",
      "title": "Receive",
      "content": "From: PUBREC\nTo: PUBREL\nCondition: pubrec received, send pubrel",
      "position": {
        "row": 25,
        "col": 0
      }
    },
    {
      "id": "desc_t_1bdadf",
      "type": "transitionDescription",
      "transitionId": "t_1bdadf",
      "title": "Wait",
      "content": "From: PUBREL\nTo: PUBCOMP\nCondition: pubrel sent, wait for pubcomp",
      "position": {
        "row": 26,
        "col": 0
      }
    },
    {
      "id": "desc_t_c269c4",
      "type": "transitionDescription",
      "transitionId": "t_c269c4",
      "title": "Receive",
      "content": "From: PUBCOMP\nTo: PUBLISH\nCondition: pubcomp received, can publish again",
      "position": {
        "row": 27,
        "col": 0
      }
    },
    {
      "id": "desc_t_eb0466",
      "type": "transitionDescription",
      "transitionId": "t_eb0466",
      "title": "Wait",
      "content": "From: SUBSCRIBE\nTo: SUBACK\nCondition: subscribe sent, wait for suback",
      "position": {
        "row": 28,
        "col": 0
      }
    },
    {
      "id": "desc_t_795104",
      "type": "transitionDescription",
      "transitionId": "t_795104",
      "title": "Receive",
      "content": "From: SUBACK\nTo: PUBLISH\nCondition: suback received, can publish",
      "position": {
        "row": 29,
        "col": 0
      }
    },
    {
      "id": "desc_t_15c023",
      "type": "transitionDescription",
      "transitionId": "t_15c023",
      "title": "Wait",
      "content": "From: UNSUBSCRIBE\nTo: UNSUBACK\nCondition: unsubscribe sent, wait for unsuback",
      "position": {
        "row": 30,
        "col": 0
      }
    },
    {
      "id": "desc_t_a55a4d",
      "type": "transitionDescription",
      "transitionId": "t_a55a4d",
      "title": "Receive",
      "content": "From: UNSUBACK\nTo: PUBLISH\nCondition: unsuback received, can publish",
      "position": {
        "row": 31,
        "col": 0
      }
    },
    {
      "id": "desc_t_b2d66c",
      "type": "transitionDescription",
      "transitionId": "t_b2d66c",
      "title": "Wait",
      "content": "From: PINGREQ\nTo: PINGRESP\nCondition: pingreq sent, wait for pingresp",
      "position": {
        "row": 32,
        "col": 0
      }
    },
    {
      "id": "desc_t_8badfc",
      "type": "transitionDescription",
      "transitionId": "t_8badfc",
      "title": "Receive",
      "content": "From: PINGRESP\nTo: PUBLISH\nCondition: pingresp received, can publish",
      "position": {
        "row": 33,
        "col": 0
      }
    },
    {
      "id": "desc_t_ff35c6",
      "type": "transitionDescription",
      "transitionId": "t_ff35c6",
      "title": "Transition",
      "content": "From: DISCONNECT\nTo: INIT\nCondition: disconnected, back to init",
      "position": {
        "row": 34,
        "col": 0
      }
    }
  ]
}